commons/__init__.py
commons/locales.py
commons/logging.py
commons/models.py
commons/runtime.py
commons/currencies/__init__.py
commons/currencies/_models.py
commons/currencies/codes.py
commons/currencies/crypto.py
commons/currencies/http/__init__.py
commons/currencies/http/clients.py
commons/currencies/payments/__init__.py
commons/currencies/payments/pix.py
commons/currencies/payments/qrcode.py
commons/database/__init__.py
commons/database/adapters.py
commons/database/cache.py
commons/database/migration.py
commons/media/__init__.py
commons/media/giphy.py
commons/media/gravatar.py
commons/media/images.py
commons/media/mimetypes.py
commons/network/__init__.py
commons/network/http/__init__.py
commons/network/http/certs.py
commons/network/http/headers.py
commons/network/http/query.py
commons_library-0.5.3.dist-info/licenses/LICENSE.md
commons_library-0.5.3.dist-info/METADATA
commons_library-0.5.3.dist-info/WHEEL
commons_library-0.5.3.dist-info/top_level.txt
commons_library-0.5.3.dist-info/RECORD
