Metadata-Version: 2.4
Name: commons-library
Version: 0.5.3
Summary: Common dependencies for Python 3 software development and data management.
Author-email: Artemis Resende <artemis@aresende.com>
License: # 🏳️‍🌈 Opinionated Queer License v1.1
Keywords: webserver,fastapi,quickstart
Classifier: Development Status :: 3 - Alpha
Classifier: Intended Audience :: Developers
Classifier: Programming Language :: Python :: 3.13
Requires-Python: >=3.13
License-File: LICENSE.md
Requires-Dist: httpx>=0.28.1
Requires-Dist: sqlmodel>=0.0.22
Requires-Dist: email-validator>=2.2.0
Requires-Dist: command-runner>=1.7.0
Requires-Dist: img2pdf>=0.6.0
Requires-Dist: pillow>=11.1.0
Requires-Dist: pycountry>=24.6.1
Requires-Dist: qrcode>=8.0
Requires-Dist: babel>=2.17.0
Requires-Dist: streams-py>=1.3.0
Dynamic: license-file
